<?xml version="1.0" encoding="UTF-8"?>
<included>
	<property name="LOGS_APP_NAME" value="crewpnr" />

	<appender name="STDOUT" class="ch.qos.logback.core.ConsoleAppender">
		<encoder>
			<charset>UTF-8</charset>
			<pattern>logback %d{HH:mm:ss.SSS} [%thread] %-5level [%-36logger{36}] - %msg%n</pattern>
		</encoder>
	</appender>

	<appender name="JOINTIBSAPILOG" class="com.lj.support.logback.appender.kinesis.FirehoseAppender">
		<bufferSize>1000</bufferSize>
		<threadCount>20</threadCount>
		<endpoint>firehose.ap-northeast-2.amazonaws.com</endpoint><!-- Specify endpointOR region -->
		<region>ap-northeast-2</region>
		<maxRetries>3</maxRetries>
		<shutdownTimeout>30</shutdownTimeout>
		<streamName>ljPrdHomeTransaction01</streamName>
		<encoding>UTF-8</encoding>
		<layout class="ch.qos.logback.classic.PatternLayout">
			<pattern>{"T":"%d{yyyy-MM-dd HH:mm:ss.SSS}","stage":"${spring.profiles.active}","level":"%level","msg":%msg,"thread":"[%thread]"}</pattern>
		</layout>
	</appender>


	<!-- Home Biz Log Appendeer -->
	<!-- <appender name="HOM_BIZ_LOG" class="com.j256.cloudwatchlogbackappender.CloudWatchAppender">
		<region>ap-northeast-2</region>
		<logGroup>PRD</logGroup>
		<logStream>${LOGS_APP_NAME}_general_log</logStream>
		<layout>
			<pattern>{
				"T"		: "%d{yyyy-MM-dd HH:mm:ss.SSS}",
				"stage"	: "${spring.profiles.active}",
				"level"	: "%level",
				"msg"	: %msg,
				"thread": "[%thread]"
			}</pattern>
		</layout>
	</appender> -->
	<appender name="HOM_BIZ_LOG" class="com.lj.support.logback.appender.kinesis.FirehoseAppender">
		<bufferSize>1000</bufferSize>
		<threadCount>20</threadCount>
		<endpoint>firehose.ap-northeast-2.amazonaws.com</endpoint><!-- Specify endpointOR region -->
		<region>ap-northeast-2</region>
		<maxRetries>3</maxRetries>
		<shutdownTimeout>30</shutdownTimeout>
		<streamName>ljPrdHomeGeneral01</streamName>
		<encoding>UTF-8</encoding>
		<layout class="ch.qos.logback.classic.PatternLayout">
			<pattern>{"T":"%d{yyyy-MM-dd HH:mm:ss.SSS}","stage":"${spring.profiles.active}","level":"%level","msg":%msg,"thread":"[%thread]"}</pattern>
		</layout>
	</appender>

	<!-- IBS 웹서비스 로그 -->
	<logger name="com.lj.support.integration.soap.interceptor.LogClientSoapInterceptor" additivity="false" level="info">
		<appender-ref ref="JOINTIBSAPILOG"/>
	</logger>
	
	<!-- LOYALTY 웹서비스 로그 -->
	<logger name="com.lj.loyalty.support.soap.LoyaltyClientInterceptor" additivity="false" level="info">
		<appender-ref ref="JOINTIBSAPILOG"/>
	</logger>

	<!-- 3rdparty Loggers -->
	<logger name="org.springframework.core" level="error" additivity="false" />
	<logger name="org.springframework.beans" level="error" additivity="false" />
	<logger name="org.springframework.context" level="error" additivity="false" />
	<logger name="org.springframework.web" level="error" additivity="false" />

	<logger name="org.apache.commons.dbcp2" level="error" additivity="false" />
	<logger name="org.apache.commons.beanutils" level="error" additivity="false" />

	<logger name="org.apache.http" level="error" additivity="false"/>

	<logger name="java.sql" level="error" additivity="false"/>
	<logger name="jdbc.sqlonly" level="error" additivity="false"/>
	<logger name="jdbc.sqltiming" level="error" additivity="false"/>
	<logger name="jdbc.audit" level="error" additivity="false"/>
	<logger name="jdbc.resultset" level="error" additivity="false"/>

	<!-- application logger -->
	<logger name="com.lj.home" additivity="true" level="info" >
		<appender-ref ref="HOM_BIZ_LOG"/>
	</logger>
	<logger name="com.lj.payment" additivity="false" level="info" >
		<appender-ref ref="HOM_BIZ_LOG"/>
	</logger>

	<root level="error">
		<appender-ref ref="STDOUT"/>
	</root>
</included>